dojson/__init__.py
dojson/__main__.py
dojson/_compat.py
dojson/errors.py
dojson/overdo.py
dojson/utils.py
dojson/version.py
dojson/cli/__init__.py
dojson/cli/command.py
dojson/cli/utils.py
dojson/contrib/__init__.py
dojson/contrib/marc21/__init__.py
dojson/contrib/marc21/model.py
dojson/contrib/marc21/utils.py
dojson/contrib/marc21/fields/__init__.py
dojson/contrib/marc21/fields/ad00x.py
dojson/contrib/marc21/fields/ad01x09x.py
dojson/contrib/marc21/fields/ad1xx3xx.py
dojson/contrib/marc21/fields/ad260360.py
dojson/contrib/marc21/fields/ad4xx.py
dojson/contrib/marc21/fields/ad5xx.py
dojson/contrib/marc21/fields/ad64x.py
dojson/contrib/marc21/fields/ad663666.py
dojson/contrib/marc21/fields/ad66768x.py
dojson/contrib/marc21/fields/ad7xx.py
dojson/contrib/marc21/fields/ad8xx.py
dojson/contrib/marc21/fields/adleader.py
dojson/contrib/marc21/fields/bd00x.py
dojson/contrib/marc21/fields/bd01x09x.py
dojson/contrib/marc21/fields/bd1xx.py
dojson/contrib/marc21/fields/bd20x24x.py
dojson/contrib/marc21/fields/bd25x28x.py
dojson/contrib/marc21/fields/bd3xx.py
dojson/contrib/marc21/fields/bd4xx.py
dojson/contrib/marc21/fields/bd5xx.py
dojson/contrib/marc21/fields/bd6xx.py
dojson/contrib/marc21/fields/bd70x75x.py
dojson/contrib/marc21/fields/bd76x78x.py
dojson/contrib/marc21/fields/bd80x83x.py
dojson/contrib/marc21/fields/bd84188x.py
dojson/contrib/marc21/fields/bdleader.py
dojson/contrib/marc21/fields/hd00x.py
dojson/contrib/marc21/fields/hd0xx.py
dojson/contrib/marc21/fields/hd3xx5xx84x.py
dojson/contrib/marc21/fields/hd85xhd88x.py
dojson/contrib/marc21/schemas/__init__.py
dojson/contrib/marc21/schemas/marc21/authority/ad-v1.0.0.json
dojson/contrib/marc21/schemas/marc21/authority/ad-v1.0.1.json
dojson/contrib/marc21/schemas/marc21/authority/ad-v1.0.2.json
dojson/contrib/marc21/schemas/marc21/authority/ad00x.json
dojson/contrib/marc21/schemas/marc21/authority/ad01x09x-v1.0.1.json
dojson/contrib/marc21/schemas/marc21/authority/ad01x09x.json
dojson-1.7.0.dist-info/licenses/AUTHORS.rst
dojson-1.7.0.dist-info/licenses/LICENSE
dojson-1.7.0.dist-info/METADATA
dojson-1.7.0.dist-info/WHEEL
dojson-1.7.0.dist-info/entry_points.txt
dojson-1.7.0.dist-info/top_level.txt
dojson-1.7.0.dist-info/RECORD
