Metadata-Version: 2.4
Name: dojson
Version: 1.7.0
Summary: DoJSON is a simple Pythonic JSON to JSON converter.
Home-page: http://github.com/inveniosoftware/dojson/
Author: Invenio collaboration
Author-email: info@inveniosoftware.org
License: BSD
Platform: any
Classifier: Intended Audience :: Developers
Classifier: License :: OSI Approved :: BSD License
Classifier: Operating System :: OS Independent
Classifier: Programming Language :: Python
Classifier: Topic :: Software Development :: Libraries :: Python Modules
Classifier: Programming Language :: Python :: 3
Classifier: Programming Language :: Python :: 3.8
Classifier: Programming Language :: Python :: 3.9
Classifier: Programming Language :: Python :: Implementation :: PyPy
Classifier: Development Status :: 4 - Beta
License-File: LICENSE
License-File: AUTHORS.rst
Requires-Dist: click>=8.1
Requires-Dist: lxml>=4.1.1
Requires-Dist: simplejson>=3.8.1
Provides-Extra: docs
Requires-Dist: Sphinx>=3; extra == "docs"
Provides-Extra: jsonschema
Requires-Dist: jsonschema>=2.5.1; extra == "jsonschema"
Provides-Extra: tests
Requires-Dist: jsonschema>=3.0; extra == "tests"
Requires-Dist: mock>=1.3.0; extra == "tests"
Requires-Dist: pytest-invenio>=1.4.0; extra == "tests"
Provides-Extra: all
Requires-Dist: Sphinx>=3; extra == "all"
Requires-Dist: jsonschema>=2.5.1; extra == "all"
Requires-Dist: jsonschema>=3.0; extra == "all"
Requires-Dist: mock>=1.3.0; extra == "all"
Requires-Dist: pytest-invenio>=1.4.0; extra == "all"
Requires-Dist: Sphinx>=3; extra == "all"
Requires-Dist: jsonschema>=2.5.1; extra == "all"
Requires-Dist: jsonschema>=3.0; extra == "all"
Requires-Dist: mock>=1.3.0; extra == "all"
Requires-Dist: pytest-invenio>=1.4.0; extra == "all"
Dynamic: author
Dynamic: author-email
Dynamic: classifier
Dynamic: description
Dynamic: home-page
Dynamic: license
Dynamic: license-file
Dynamic: platform
Dynamic: provides-extra
Dynamic: requires-dist
Dynamic: summary
